{"GlobalPropertiesHash":"g26jXacPqqwELJzcuvigI8pFQihdG/V4lmiZevQEujM=","FingerprintPatternsHash":"gq3WsqcKBUGTSNle7RKKyXRIwh7M8ccEqOqYvIzoM04=","PropertyOverridesHash":"8ZRc1sGeVrPBx4lD717BgRaQekyh78QKV9SKsdt638U=","InputHashes":["nGcRpkrrxWokIzR/\u002BFakPCcG7WKMRu3R5Ay2SBSsrwY=","J8zsmXBLO8M8YSBbzWakhvTayZbhS2fR5lOOCDr00Ag=","BiZDyiO4GufQ1DpPvLjG8bAHkEqvX1R3\u002B5LQyjgcfgU=","tHZxfaGrD3cFLtf5ESXDk3yCX297XIAdgcAXMW/ao7k="],"CachedAssets":{"J8zsmXBLO8M8YSBbzWakhvTayZbhS2fR5lOOCDr00Ag=":{"Identity":"C:\\Users\\Usuario\\source\\repos\\neocore-bureau\\backend\\Master\\wwwroot\\logoWhiteSmall.png","SourceId":"Master","SourceType":"Discovered","ContentRoot":"C:\\Users\\Usuario\\source\\repos\\neocore-bureau\\backend\\Master\\wwwroot\\","BasePath":"/","RelativePath":"logoWhiteSmall#[.{fingerprint}]?.png","AssetKind":"All","AssetMode":"All","AssetRole":"Primary","AssetMergeBehavior":null,"AssetMergeSource":"","RelatedAsset":null,"AssetTraitName":null,"AssetTraitValue":null,"Fingerprint":"xjqsdun63x","Integrity":"kzUoKPREkqnS9ABf4gX/XcDFJDtp\u002ButZZKEbtqJKTIQ=","CopyToOutputDirectory":"Always","CopyToPublishDirectory":"PreserveNewest","OriginalItemSpec":"wwwroot\\logoWhiteSmall.png","FileLength":9976,"LastWriteTime":"2026-01-25T14:16:20.5132919+00:00"},"nGcRpkrrxWokIzR/\u002BFakPCcG7WKMRu3R5Ay2SBSsrwY=":{"Identity":"C:\\Users\\Usuario\\source\\repos\\neocore-bureau\\backend\\Master\\wwwroot\\favicon.ico","SourceId":"Master","SourceType":"Discovered","ContentRoot":"C:\\Users\\Usuario\\source\\repos\\neocore-bureau\\backend\\Master\\wwwroot\\","BasePath":"/","RelativePath":"favicon#[.{fingerprint}]?.ico","AssetKind":"All","AssetMode":"All","AssetRole":"Primary","AssetMergeBehavior":null,"AssetMergeSource":"","RelatedAsset":null,"AssetTraitName":null,"AssetTraitValue":null,"Fingerprint":"ct7bsim7k8","Integrity":"UECIacUpw5hWpPRgDRUiyHyGWKqN2ZJZmGWZL675/EE=","CopyToOutputDirectory":"Always","CopyToPublishDirectory":"PreserveNewest","OriginalItemSpec":"wwwroot\\favicon.ico","FileLength":6294,"LastWriteTime":"2025-10-20T17:01:48.9502289+00:00"}},"CachedCopyCandidates":{}}